haruko/__init__.py
haruko/haruko.py
haruko-1.0.14.dist-info/LICENSE
haruko-1.0.14.dist-info/METADATA
haruko-1.0.14.dist-info/WHEEL
haruko-1.0.14.dist-info/entry_points.txt
haruko-1.0.14.dist-info/top_level.txt
haruko-1.0.14.dist-info/RECORD
