Metadata-Version: 2.1
Name: haruko
Version: 1.0.14
Summary: An Advanced Password Wordlist Generator for Brute-Force an Dictionary Attacks
Home-page: https://github.com/veilwr4ith/Haruko
Author: Veilwr4ith
Author-email: hacktheveil@gmail.com
License: UNKNOWN
Platform: UNKNOWN
Classifier: Programming Language :: Python :: 3
Classifier: License :: OSI Approved :: MIT License
Classifier: Operating System :: OS Independent
Requires-Python: >=3.10
License-File: LICENSE
